tezapi/__init__.py
tezapi/app.py
tezapi/middleware.py
tezapi/responses.py
tezapi/router_field.py
tezapi/routes.py
tezapi/schemas.py
tezapi/templating.py
tezapi/exceptions/__init__.py
tezapi/exceptions/apiexception.py
tezapi/exceptions/base_exceptions.py
tezapi/exceptions/catching_exc.py
tezapi-0.0.6.dist-info/LICENSE
tezapi-0.0.6.dist-info/METADATA
tezapi-0.0.6.dist-info/WHEEL
tezapi-0.0.6.dist-info/top_level.txt
tezapi-0.0.6.dist-info/RECORD
