Metadata-Version: 2.1
Name: tezapi
Version: 0.0.6
Summary: Asynchronous web framework for building powerful web APIs and applications with Python
Author-email: dev-au <devaubusiness@gmail.com>
Project-URL: Homepage, https://github.com/dev-au/tezapi
Project-URL: Issues, https://github.com/dev-au/tezapi/issues
Classifier: Programming Language :: Python :: 3
Classifier: License :: OSI Approved :: MIT License
Classifier: Operating System :: OS Independent
Requires-Python: >=3.8
License-File: LICENSE
Requires-Dist: aiohttp ~=3.9.5
Requires-Dist: jinja2 ~=3.1.4
